spectro_inlets_quantification/__init__.py
spectro_inlets_quantification/calibration.py
spectro_inlets_quantification/chip.py
spectro_inlets_quantification/compatability.py
spectro_inlets_quantification/config.py
spectro_inlets_quantification/constants.py
spectro_inlets_quantification/custom_types.py
spectro_inlets_quantification/exceptions.py
spectro_inlets_quantification/medium.py
spectro_inlets_quantification/mixture.py
spectro_inlets_quantification/molecule.py
spectro_inlets_quantification/peak.py
spectro_inlets_quantification/quantifier.py
spectro_inlets_quantification/sensitivity.py
spectro_inlets_quantification/signal.py
spectro_inlets_quantification/tools.py
spectro_inlets_quantification/data/chips/standard.yml
spectro_inlets_quantification/data/molecules/Ar.yml
spectro_inlets_quantification/data/molecules/C2H4.yml
spectro_inlets_quantification/data/molecules/CH4.yml
spectro_inlets_quantification/data/molecules/CO.yml
spectro_inlets_quantification/data/molecules/CO2.yml
spectro_inlets_quantification/data/molecules/H2.yml
spectro_inlets_quantification/data/molecules/H2O.yml
spectro_inlets_quantification/data/molecules/He.yml
spectro_inlets_quantification/data/molecules/N2.yml
spectro_inlets_quantification/data/molecules/O2.yml
spectro_inlets_quantification-1.2.4.dist-info/AUTHORS
spectro_inlets_quantification-1.2.4.dist-info/METADATA
spectro_inlets_quantification-1.2.4.dist-info/WHEEL
spectro_inlets_quantification-1.2.4.dist-info/top_level.txt
spectro_inlets_quantification-1.2.4.dist-info/RECORD
