Metadata-Version: 2.1
Name: spectro-inlets-quantification
Version: 1.2.4
Summary: The ECMS quantification package
Author-email: Spectro Inlets <software@spectroinlets.com>
License: # DUAL LICENSE CONDITIONS
Project-URL: Homepage, https://github.com/SpectroInlets/spectro_inlets_quantification
Project-URL: Bug Tracker, https://github.com/SpectroInlets/spectro_inlets_quantification/issues
Keywords: ECMS,quantification,data treatment
Classifier: Programming Language :: Python :: 3.7
Classifier: Programming Language :: Python :: 3.8
Classifier: Programming Language :: Python :: 3.9
Classifier: Programming Language :: Python :: 3.10
Classifier: License :: Other/Proprietary License
Classifier: Operating System :: OS Independent
Classifier: Topic :: Scientific/Engineering :: Chemistry
Requires-Python: >=3.7
License-File: AUTHORS
Requires-Dist: numpy >=1.24.3
Requires-Dist: scipy >=1.10.1
Requires-Dist: matplotlib >=3.7.1
Requires-Dist: pandas >=2.0.2
Requires-Dist: attrs >=23.1.0
Requires-Dist: PyYAML >=6.0.1
Provides-Extra: rest
Requires-Dist: docutils >=0.3 ; extra == 'rest'
Requires-Dist: pack ==1.1,==1.3 ; extra == 'rest'
